doSetup/__init__.py
doSetup/examples.py
doSetup-0.1.dist-info/METADATA
doSetup-0.1.dist-info/WHEEL
doSetup-0.1.dist-info/top_level.txt
doSetup-0.1.dist-info/RECORD
