Metadata-Version: 2.1
Name: doSetup
Version: 0.1
Summary: Next GEN PyQt to create the interface
Home-page: https://www.google.com/
Author: Mark Bulah
Author-email: markbulah@mail.ru
Classifier: Programming Language :: Python :: 3
Classifier: License :: OSI Approved :: MIT License
Classifier: Operating System :: OS Independent
Requires-Python: >=3.6
